README.txt
setup.py
Tasks_Tracker.egg-info/PKG-INFO
Tasks_Tracker.egg-info/SOURCES.txt
Tasks_Tracker.egg-info/dependency_links.txt
Tasks_Tracker.egg-info/entry_points.txt
Tasks_Tracker.egg-info/requires.txt
Tasks_Tracker.egg-info/top_level.txt
pytasks/__init__.py
pytasks/main.py
pytasks/lib/__init__.py
pytasks/lib/_bzrversion.py
pytasks/lib/rtm.py
pytasks/lib/tasks.py
pytasks/lib/versionlib.py
pytasks/unittests/__init__.py
pytasks/unittests/test_main.py
pytasks/unittests/test_tasks.py