Metadata-Version: 1.0
Name: Tasks-Tracker
Version: 0.92
Summary: A simple command line project task tracking tool.
Home-page: https://launchpad.net/tasks-tracker
Author: Mohamed Diarra
Author-email: moh@softwebia.com
License: 
